rover_position_rjg/__init__.py
rover_position_rjg/monitor.py
rover_position_rjg/service.py
rover_position_rjg/clients/__init__.py
rover_position_rjg/clients/calibration/__init__.py
rover_position_rjg/clients/calibration/decawave/__init__.py
rover_position_rjg/clients/calibration/decawave/decawave_rotation.py
rover_position_rjg/clients/calibration/decawave/layout.py
rover_position_rjg/clients/calibration/imu/__init__.py
rover_position_rjg/clients/calibration/imu/adjust_biases.py
rover_position_rjg/clients/calibration/imu/calibrate.py
rover_position_rjg/clients/calibration/imu/imu_calibrator.py
rover_position_rjg/clients/monitor/__init__.py
rover_position_rjg/clients/monitor/app.py
rover_position_rjg/clients/monitor/imu_data_model.py
rover_position_rjg/clients/monitor/message_switch.py
rover_position_rjg/clients/monitor/messenger.py
rover_position_rjg/clients/monitor/monitor.py
rover_position_rjg/clients/monitor/presenter.py
rover_position_rjg/clients/monitor/view.py
rover_position_rjg/csv_helpers/__init__.py
rover_position_rjg/csv_helpers/attitude_output_csv_converter.py
rover_position_rjg/csv_helpers/csv_converter.py
rover_position_rjg/csv_helpers/csv_reader.py
rover_position_rjg/csv_helpers/csv_writer.py
rover_position_rjg/csv_helpers/data_csv_converter.py
rover_position_rjg/csv_helpers/position_csv_converter.py
rover_position_rjg/csv_helpers/quaternion_csv_converter.py
rover_position_rjg/csv_helpers/vector_csv_converter.py
rover_position_rjg/data/__init__.py
rover_position_rjg/data/data.py
rover_position_rjg/data/data_filter.py
rover_position_rjg/data/data_value_csv_converter.py
rover_position_rjg/data/flags.py
rover_position_rjg/data/quaternion.py
rover_position_rjg/data/vector.py
rover_position_rjg/data/data_pump/__init__.py
rover_position_rjg/data/data_pump/data_provider.py
rover_position_rjg/data/data_pump/data_pump.py
rover_position_rjg/data/data_pump/process_data_pump.py
rover_position_rjg/data/data_pump/rate_limited_data_provider.py
rover_position_rjg-0.1.8.dist-info/LICENSE.txt
rover_position_rjg-0.1.8.dist-info/METADATA
rover_position_rjg-0.1.8.dist-info/WHEEL
rover_position_rjg-0.1.8.dist-info/top_level.txt
rover_position_rjg-0.1.8.dist-info/RECORD
